LICENSE
MANIFEST.in
README.md
setup.cfg
setup.py
conf/rbl.conf.dist
src/domainmagic/__init__.py
src/domainmagic/dnslookup.py
src/domainmagic/extractor.py
src/domainmagic/filelock.py
src/domainmagic/fileupdate.py
src/domainmagic/ip.py
src/domainmagic/mailaddr.py
src/domainmagic/rbl.py
src/domainmagic/tasker.py
src/domainmagic/threadpool.py
src/domainmagic/tld.py
src/domainmagic/util.py
src/domainmagic/validators.py
src/domainmagic.egg-info/PKG-INFO
src/domainmagic.egg-info/SOURCES.txt
src/domainmagic.egg-info/dependency_links.txt
src/domainmagic.egg-info/requires.txt
src/domainmagic.egg-info/top_level.txt