Metadata-Version: 2.1
Name: domainmagic
Version: 0.0.17
Summary: Python library for all sorts of domain lookup related stuff (rbl lookups, extractors etc)
Home-page: https://gitlab.com/fumail/domainmagic
Download-URL: https://gitlab.com/fumail/domainmagic/-/archive/master/domainmagic-master.tar.bz2
Author: O. Schacher
Author-email: oli@fuglu.org
License: Apache Software License
Classifier: Development Status :: 3 - Alpha
Classifier: Topic :: Internet :: Name Service (DNS)
Classifier: Environment :: No Input/Output (Daemon)
Classifier: Intended Audience :: Developers
Classifier: Intended Audience :: System Administrators
Classifier: License :: OSI Approved :: Apache Software License
Classifier: Operating System :: POSIX
Classifier: Programming Language :: Python
License-File: LICENSE
